<root>
<class>
	<thumbnail>Big_Knight</thumbnail>
	<desc>Le Chevalier est un couard. Une chiffe molle. Bonne chance pour réveiller ce gros tas de muscles.
	Quand le Chevalier lance son sort,il déclenche une vague de rage infligeant
	des dégâts autour de lui.
	C'est le seul sortilège dont la puissance dépend du temps de chargement.</desc>
</class>
<class>
	<thumbnail>Big_NoCharacterGuy</thumbnail>
	<desc>
	"Mets une écharpe, tu vas attraper froid dehors."
	
	- Maman</desc>
</class>
<class>
	<thumbnail>Big_Magician</thumbnail>
	<desc>
	Sous ce chapeau vieux et sale se cache la sagesse des anciens, combinée à des années
	de taverne. Le magicien peut s'effondrer ivre mort au milieu d'une bataille
	ou déchaîner la colère des glaces.
	
	Son sortilège favori gèle les adversaires à portée pendant
	quelques secondes. Utilisez ce temps pour reprendre l'avantage !
	</desc>
</class>
</root>